{
  "schemaVersion": 1,
  "app": "biubiubiu_android",
  "date": "2026-07-04",
  "month": "2026-07",
  "updatedAt": "2026-07-03T18:10:47.992Z",
  "paths": {
    "counter": "archive/counters/2026/07/2026-07-04.json",
    "summary": "archive/summary/2026/2026-07.json"
  },
  "totals": {
    "date": "2026-07-04",
    "activeUsers": 44,
    "activeDevices": 67,
    "danmuSent": 23673,
    "discussionSent": 530,
    "danmuFailed": 0,
    "discussionFailed": 0,
    "danmuSkipped": 0,
    "lastSeenAt": "2026-07-04T02:10:25.667759",
    "updatedAt": "2026-07-03T18:10:46.558Z"
  },
  "users": [
    {
      "weiboNickname": "зҙ йўңеӨҡеӨҡJC-T",
      "activeDevices": 5,
      "danmuSent": 6100,
      "discussionSent": 0,
      "danmuFailed": 0,
      "discussionFailed": 0,
      "danmuSkipped": 0,
      "totalSent": 6100,
      "lastSeenAt": "2026-07-04T02:10:25.667759"
    },
    {
      "weiboNickname": "зәўдёқдёқе„ҝ",
      "activeDevices": 9,
      "danmuSent": 3491,
      "discussionSent": 0,
      "danmuFailed": 0,
      "discussionFailed": 0,
      "danmuSkipped": 0,
      "totalSent": 3491,
      "lastSeenAt": "2026-07-04T02:08:55.248308"
    },
    {
      "weiboNickname": "зі–дёҚеҘҪеҗғ--YZZ",
      "activeDevices": 1,
      "danmuSent": 1206,
      "discussionSent": 0,
      "danmuFailed": 0,
      "discussionFailed": 0,
      "danmuSkipped": 0,
      "totalSent": 1206,
      "lastSeenAt": "2026-07-04T02:08:12.557084"
    },
    {
      "weiboNickname": "жӘҖдәҶйў—зі–",
      "activeDevices": 2,
      "danmuSent": 901,
      "discussionSent": 0,
      "danmuFailed": 0,
      "discussionFailed": 0,
      "danmuSkipped": 0,
      "totalSent": 901,
      "lastSeenAt": "2026-07-04T01:54:02.889702"
    },
    {
      "weiboNickname": "Mr_Tanе°ҸзҢ«",
      "activeDevices": 2,
      "danmuSent": 894,
      "discussionSent": 0,
      "danmuFailed": 0,
      "discussionFailed": 0,
      "danmuSkipped": 0,
      "totalSent": 894,
      "lastSeenAt": "2026-07-04T01:52:13.458752"
    },
    {
      "weiboNickname": "зӮӯзҒ«зӮҷз¬јеҢ…",
      "activeDevices": 1,
      "danmuSent": 828,
      "discussionSent": 0,
      "danmuFailed": 0,
      "discussionFailed": 0,
      "danmuSkipped": 0,
      "totalSent": 828,
      "lastSeenAt": "2026-07-04T02:09:58.574466"
    },
    {
      "weiboNickname": "жЎ”жў—иҠұ",
      "activeDevices": 3,
      "danmuSent": 702,
      "discussionSent": 100,
      "danmuFailed": 0,
      "discussionFailed": 0,
      "danmuSkipped": 0,
      "totalSent": 802,
      "lastSeenAt": "2026-07-04T02:05:13.732910"
    },
    {
      "weiboNickname": "еӨҡеӨҡеҸҲmanеҸҲhealthy",
      "activeDevices": 1,
      "danmuSent": 747,
      "discussionSent": 0,
      "danmuFailed": 0,
      "discussionFailed": 0,
      "danmuSkipped": 0,
      "totalSent": 747,
      "lastSeenAt": "2026-07-04T02:04:18.780551"
    },
    {
      "weiboNickname": "е‘Ҷе‘Ҷзҡ„еҸҜзҲұеӨҡ_",
      "activeDevices": 2,
      "danmuSent": 728,
      "discussionSent": 0,
      "danmuFailed": 0,
      "discussionFailed": 0,
      "danmuSkipped": 0,
      "totalSent": 728,
      "lastSeenAt": "2026-07-04T02:09:41.289837"
    },
    {
      "weiboNickname": "йӮұйӮұT-HooHoo",
      "activeDevices": 1,
      "danmuSent": 700,
      "discussionSent": 0,
      "danmuFailed": 0,
      "discussionFailed": 0,
      "danmuSkipped": 0,
      "totalSent": 700,
      "lastSeenAt": "2026-07-04T02:06:23.333306"
    },
    {
      "weiboNickname": "е°Ҹйқҷе§қеҗ–",
      "activeDevices": 1,
      "danmuSent": 671,
      "discussionSent": 0,
      "danmuFailed": 0,
      "discussionFailed": 0,
      "danmuSkipped": 0,
      "totalSent": 671,
      "lastSeenAt": "2026-07-04T01:55:03.835947"
    },
    {
      "weiboNickname": "е№іжӘҖдёҖз”ҹ",
      "activeDevices": 2,
      "danmuSent": 667,
      "discussionSent": 0,
      "danmuFailed": 0,
      "discussionFailed": 0,
      "danmuSkipped": 0,
      "totalSent": 667,
      "lastSeenAt": "2026-07-04T02:05:49.277565"
    },
    {
      "weiboNickname": "жӘҖдәҶдёӘз§ҳеҜҶеҗҚ",
      "activeDevices": 1,
      "danmuSent": 600,
      "discussionSent": 0,
      "danmuFailed": 0,
      "discussionFailed": 0,
      "danmuSkipped": 0,
      "totalSent": 600,
      "lastSeenAt": "2026-07-04T02:04:50.485846"
    },
    {
      "weiboNickname": "д№ҰиҚ’дәәеЈ«",
      "activeDevices": 1,
      "danmuSent": 534,
      "discussionSent": 0,
      "danmuFailed": 0,
      "discussionFailed": 0,
      "danmuSkipped": 0,
      "totalSent": 534,
      "lastSeenAt": "2026-07-04T01:47:55.703799"
    },
    {
      "weiboNickname": "е“Ҷе•Ұ_T-HooHoo_",
      "activeDevices": 1,
      "danmuSent": 500,
      "discussionSent": 0,
      "danmuFailed": 0,
      "discussionFailed": 0,
      "danmuSkipped": 0,
      "totalSent": 500,
      "lastSeenAt": "2026-07-04T02:05:03.016034"
    },
    {
      "weiboNickname": "з”ңиұҶзҡ„T-hoohoo",
      "activeDevices": 1,
      "danmuSent": 468,
      "discussionSent": 0,
      "danmuFailed": 0,
      "discussionFailed": 0,
      "danmuSkipped": 0,
      "totalSent": 468,
      "lastSeenAt": "2026-07-04T01:59:47.402665"
    },
    {
      "weiboNickname": "еҚҠе”ҜT-HooHoo",
      "activeDevices": 1,
      "danmuSent": 463,
      "discussionSent": 0,
      "danmuFailed": 0,
      "discussionFailed": 0,
      "danmuSkipped": 0,
      "totalSent": 463,
      "lastSeenAt": "2026-07-04T01:59:05.761772"
    },
    {
      "weiboNickname": "жӘҖжӘҖйўңйўң",
      "activeDevices": 2,
      "danmuSent": 402,
      "discussionSent": 0,
      "danmuFailed": 0,
      "discussionFailed": 0,
      "danmuSkipped": 0,
      "totalSent": 402,
      "lastSeenAt": "2026-07-04T02:05:12.222322"
    },
    {
      "weiboNickname": "з©ҝи¶ҠжңҲе…үд№Ӣеўғ",
      "activeDevices": 1,
      "danmuSent": 400,
      "discussionSent": 0,
      "danmuFailed": 0,
      "discussionFailed": 0,
      "danmuSkipped": 0,
      "totalSent": 400,
      "lastSeenAt": "2026-07-04T01:40:19.246583"
    },
    {
      "weiboNickname": "жӘҖзҢ«зҢ«зҡ„е®қиҙқ",
      "activeDevices": 1,
      "danmuSent": 400,
      "discussionSent": 0,
      "danmuFailed": 0,
      "discussionFailed": 0,
      "danmuSkipped": 0,
      "totalSent": 400,
      "lastSeenAt": "2026-07-04T01:47:15.930937"
    },
    {
      "weiboNickname": "Glory-JCT",
      "activeDevices": 2,
      "danmuSent": 0,
      "discussionSent": 400,
      "danmuFailed": 0,
      "discussionFailed": 0,
      "danmuSkipped": 0,
      "totalSent": 400,
      "lastSeenAt": "2026-07-04T02:06:28.590497"
    },
    {
      "weiboNickname": "зҗӣе°ҸиҸ“_иҸ“ж»ЎеҚҙеұұ",
      "activeDevices": 1,
      "danmuSent": 253,
      "discussionSent": 0,
      "danmuFailed": 0,
      "discussionFailed": 0,
      "danmuSkipped": 0,
      "totalSent": 253,
      "lastSeenAt": "2026-07-04T02:10:04.776229"
    },
    {
      "weiboNickname": "иәәе°ёзҡ„з«№йҖҗй©»зҢӘ",
      "activeDevices": 1,
      "danmuSent": 200,
      "discussionSent": 30,
      "danmuFailed": 0,
      "discussionFailed": 0,
      "danmuSkipped": 0,
      "totalSent": 230,
      "lastSeenAt": "2026-07-04T01:44:14.805962"
    },
    {
      "weiboNickname": "жө”жңҲжһ«",
      "activeDevices": 1,
      "danmuSent": 213,
      "discussionSent": 0,
      "danmuFailed": 0,
      "discussionFailed": 0,
      "danmuSkipped": 0,
      "totalSent": 213,
      "lastSeenAt": "2026-07-04T01:46:31.182354"
    },
    {
      "weiboNickname": "дё–з•ҢеҰӮжӯӨзҫҺеҘҪ1988",
      "activeDevices": 2,
      "danmuSent": 201,
      "discussionSent": 0,
      "danmuFailed": 0,
      "discussionFailed": 0,
      "danmuSkipped": 0,
      "totalSent": 201,
      "lastSeenAt": "2026-07-04T00:49:22.533707"
    },
    {
      "weiboNickname": "ж¬Ўж¬ЎзҡҶеҰӮеҲқи§Ғ",
      "activeDevices": 1,
      "danmuSent": 200,
      "discussionSent": 0,
      "danmuFailed": 0,
      "discussionFailed": 0,
      "danmuSkipped": 0,
      "totalSent": 200,
      "lastSeenAt": "2026-07-04T01:36:19.870813"
    },
    {
      "weiboNickname": "и·Ҝе…®жі•е°”HooHoo-T",
      "activeDevices": 1,
      "danmuSent": 200,
      "discussionSent": 0,
      "danmuFailed": 0,
      "discussionFailed": 0,
      "danmuSkipped": 0,
      "totalSent": 200,
      "lastSeenAt": "2026-07-04T01:40:06.367960"
    },
    {
      "weiboNickname": "ChiaLin5415",
      "activeDevices": 1,
      "danmuSent": 143,
      "discussionSent": 0,
      "danmuFailed": 0,
      "discussionFailed": 0,
      "danmuSkipped": 0,
      "totalSent": 143,
      "lastSeenAt": "2026-07-04T00:11:54.795041"
    },
    {
      "weiboNickname": "е°ҸжӘҖзҡ„HooеҙҪ",
      "activeDevices": 1,
      "danmuSent": 142,
      "discussionSent": 0,
      "danmuFailed": 0,
      "discussionFailed": 0,
      "danmuSkipped": 0,
      "totalSent": 142,
      "lastSeenAt": "2026-07-04T00:41:16.830374"
    },
    {
      "weiboNickname": "SarahзҢ«е°Ҹе’Ә",
      "activeDevices": 1,
      "danmuSent": 101,
      "discussionSent": 0,
      "danmuFailed": 0,
      "discussionFailed": 0,
      "danmuSkipped": 0,
      "totalSent": 101,
      "lastSeenAt": "2026-07-04T01:55:32.735789"
    },
    {
      "weiboNickname": "еӨҡеҠ зӮ№зі–1005",
      "activeDevices": 2,
      "danmuSent": 100,
      "discussionSent": 0,
      "danmuFailed": 0,
      "discussionFailed": 0,
      "danmuSkipped": 0,
      "totalSent": 100,
      "lastSeenAt": "2026-07-04T01:48:42.455852"
    },
    {
      "weiboNickname": "зҹўжёқyu",
      "activeDevices": 1,
      "danmuSent": 100,
      "discussionSent": 0,
      "danmuFailed": 0,
      "discussionFailed": 0,
      "danmuSkipped": 0,
      "totalSent": 100,
      "lastSeenAt": "2026-07-04T00:24:51.297844"
    },
    {
      "weiboNickname": "жӘҖзҗҙйӣ…иҮҙHooHoo",
      "activeDevices": 1,
      "danmuSent": 100,
      "discussionSent": 0,
      "danmuFailed": 0,
      "discussionFailed": 0,
      "danmuSkipped": 0,
      "totalSent": 100,
      "lastSeenAt": "2026-07-04T01:46:38.401369"
    },
    {
      "weiboNickname": "д»ҷеҘіPinkзҲұз§ҚиҚү",
      "activeDevices": 1,
      "danmuSent": 100,
      "discussionSent": 0,
      "danmuFailed": 0,
      "discussionFailed": 0,
      "danmuSkipped": 0,
      "totalSent": 100,
      "lastSeenAt": "2026-07-04T00:49:00.462185"
    },
    {
      "weiboNickname": "жІҒиҠі520",
      "activeDevices": 1,
      "danmuSent": 73,
      "discussionSent": 0,
      "danmuFailed": 0,
      "discussionFailed": 0,
      "danmuSkipped": 0,
      "totalSent": 73,
      "lastSeenAt": "2026-07-04T00:22:24.542691"
    },
    {
      "weiboNickname": "иөҙжӘҖд№ӢзәҰ-JCT",
      "activeDevices": 1,
      "danmuSent": 71,
      "discussionSent": 0,
      "danmuFailed": 0,
      "discussionFailed": 0,
      "danmuSkipped": 0,
      "totalSent": 71,
      "lastSeenAt": "2026-07-04T00:57:58.061977"
    },
    {
      "weiboNickname": "ReжҷЁжӣҰ-",
      "activeDevices": 1,
      "danmuSent": 31,
      "discussionSent": 0,
      "danmuFailed": 0,
      "discussionFailed": 0,
      "danmuSkipped": 0,
      "totalSent": 31,
      "lastSeenAt": "2026-07-04T00:30:30.153355"
    },
    {
      "weiboNickname": "жӘҖеҒҘж¬ЎжҲ‘еңЁеҚ—е®ҒзӯүдҪ ",
      "activeDevices": 1,
      "danmuSent": 26,
      "discussionSent": 0,
      "danmuFailed": 0,
      "discussionFailed": 0,
      "danmuSkipped": 0,
      "totalSent": 26,
      "lastSeenAt": "2026-07-04T00:04:46.855936"
    },
    {
      "weiboNickname": "ж¬Ўж¬ЎеҫҲеҒҘеә·",
      "activeDevices": 1,
      "danmuSent": 16,
      "discussionSent": 0,
      "danmuFailed": 0,
      "discussionFailed": 0,
      "danmuSkipped": 0,
      "totalSent": 16,
      "lastSeenAt": "2026-07-04T00:09:20.019082"
    },
    {
      "weiboNickname": "е°Ҹе°Ҹе°Ҹе°Ҹе…”Q",
      "activeDevices": 1,
      "danmuSent": 1,
      "discussionSent": 0,
      "danmuFailed": 0,
      "discussionFailed": 0,
      "danmuSkipped": 0,
      "totalSent": 1,
      "lastSeenAt": "2026-07-04T00:02:33.815994"
    },
    {
      "weiboNickname": "жҷЁе…үеҫ®жҡ–JCT",
      "activeDevices": 1,
      "danmuSent": 0,
      "discussionSent": 0,
      "danmuFailed": 0,
      "discussionFailed": 0,
      "danmuSkipped": 0,
      "totalSent": 0,
      "lastSeenAt": "2026-07-04T02:00:19.643046"
    },
    {
      "weiboNickname": "жңӘз»‘е®ҡжҳөз§°",
      "activeDevices": 1,
      "danmuSent": 0,
      "discussionSent": 0,
      "danmuFailed": 0,
      "discussionFailed": 0,
      "danmuSkipped": 0,
      "totalSent": 0,
      "lastSeenAt": "2026-07-04T01:18:06.522833"
    },
    {
      "weiboNickname": "е№ёиҝҗе°Ҹзҫ”зҫҠ",
      "activeDevices": 2,
      "danmuSent": 0,
      "discussionSent": 0,
      "danmuFailed": 0,
      "discussionFailed": 0,
      "danmuSkipped": 0,
      "totalSent": 0,
      "lastSeenAt": "2026-07-04T00:19:51.050278"
    },
    {
      "weiboNickname": "AAAзӮ«иһәиӣізІүзҗӘе§җ",
      "activeDevices": 1,
      "danmuSent": 0,
      "discussionSent": 0,
      "danmuFailed": 0,
      "discussionFailed": 0,
      "danmuSkipped": 0,
      "totalSent": 0,
      "lastSeenAt": "2026-07-04T01:17:31.152792"
    }
  ]
}
