{
  "schemaVersion": 1,
  "app": "biubiubiu_android",
  "date": "2026-07-05",
  "month": "2026-07",
  "updatedAt": "2026-07-04T18:37:01.032Z",
  "paths": {
    "counter": "archive/counters/2026/07/2026-07-05.json",
    "summary": "archive/summary/2026/2026-07.json"
  },
  "totals": {
    "date": "2026-07-05",
    "activeUsers": 47,
    "activeDevices": 69,
    "danmuSent": 37854,
    "discussionSent": 3167,
    "danmuFailed": 0,
    "discussionFailed": 0,
    "danmuSkipped": 0,
    "lastSeenAt": "2026-07-05T02:36:52.547199",
    "updatedAt": "2026-07-04T18:36:59.612Z"
  },
  "users": [
    {
      "weiboNickname": "素颜多多JC-T",
      "activeDevices": 5,
      "danmuSent": 7009,
      "discussionSent": 0,
      "danmuFailed": 0,
      "discussionFailed": 0,
      "danmuSkipped": 0,
      "totalSent": 7009,
      "lastSeenAt": "2026-07-05T02:34:07.972817"
    },
    {
      "weiboNickname": "红丝丝儿",
      "activeDevices": 9,
      "danmuSent": 4231,
      "discussionSent": 0,
      "danmuFailed": 0,
      "discussionFailed": 0,
      "danmuSkipped": 0,
      "totalSent": 4231,
      "lastSeenAt": "2026-07-05T02:35:52.822147"
    },
    {
      "weiboNickname": "炭火炙笼包",
      "activeDevices": 1,
      "danmuSent": 2814,
      "discussionSent": 0,
      "danmuFailed": 0,
      "discussionFailed": 0,
      "danmuSkipped": 0,
      "totalSent": 2814,
      "lastSeenAt": "2026-07-05T02:29:34.968145"
    },
    {
      "weiboNickname": "邱邱T-HooHoo",
      "activeDevices": 1,
      "danmuSent": 2377,
      "discussionSent": 0,
      "danmuFailed": 0,
      "discussionFailed": 0,
      "danmuSkipped": 0,
      "totalSent": 2377,
      "lastSeenAt": "2026-07-05T02:09:57.664475"
    },
    {
      "weiboNickname": "糖不好吃--YZZ",
      "activeDevices": 2,
      "danmuSent": 1857,
      "discussionSent": 0,
      "danmuFailed": 0,
      "discussionFailed": 0,
      "danmuSkipped": 0,
      "totalSent": 1857,
      "lastSeenAt": "2026-07-05T02:35:11.893354"
    },
    {
      "weiboNickname": "桔梗花",
      "activeDevices": 3,
      "danmuSent": 1791,
      "discussionSent": 0,
      "danmuFailed": 0,
      "discussionFailed": 0,
      "danmuSkipped": 0,
      "totalSent": 1791,
      "lastSeenAt": "2026-07-05T02:30:02.593381"
    },
    {
      "weiboNickname": "浓缩苦橙加冰茶",
      "activeDevices": 1,
      "danmuSent": 1607,
      "discussionSent": 0,
      "danmuFailed": 0,
      "discussionFailed": 0,
      "danmuSkipped": 0,
      "totalSent": 1607,
      "lastSeenAt": "2026-07-05T02:36:52.547199"
    },
    {
      "weiboNickname": "檀了颗糖",
      "activeDevices": 2,
      "danmuSent": 1500,
      "discussionSent": 0,
      "danmuFailed": 0,
      "discussionFailed": 0,
      "danmuSkipped": 0,
      "totalSent": 1500,
      "lastSeenAt": "2026-07-05T02:30:45.095385"
    },
    {
      "weiboNickname": "晨光微暖JCT",
      "activeDevices": 2,
      "danmuSent": 1464,
      "discussionSent": 0,
      "danmuFailed": 0,
      "discussionFailed": 0,
      "danmuSkipped": 0,
      "totalSent": 1464,
      "lastSeenAt": "2026-07-05T02:29:28.768903"
    },
    {
      "weiboNickname": "Glory-JCT",
      "activeDevices": 2,
      "danmuSent": 1160,
      "discussionSent": 0,
      "danmuFailed": 0,
      "discussionFailed": 0,
      "danmuSkipped": 0,
      "totalSent": 1160,
      "lastSeenAt": "2026-07-05T02:25:54.000365"
    },
    {
      "weiboNickname": "平檀一生",
      "activeDevices": 2,
      "danmuSent": 0,
      "discussionSent": 960,
      "danmuFailed": 0,
      "discussionFailed": 0,
      "danmuSkipped": 0,
      "totalSent": 960,
      "lastSeenAt": "2026-07-05T02:29:58.252963"
    },
    {
      "weiboNickname": "多多又man又healthy",
      "activeDevices": 1,
      "danmuSent": 900,
      "discussionSent": 0,
      "danmuFailed": 0,
      "discussionFailed": 0,
      "danmuSkipped": 0,
      "totalSent": 900,
      "lastSeenAt": "2026-07-05T02:29:51.728489"
    },
    {
      "weiboNickname": "小静姝吖",
      "activeDevices": 1,
      "danmuSent": 900,
      "discussionSent": 0,
      "danmuFailed": 0,
      "discussionFailed": 0,
      "danmuSkipped": 0,
      "totalSent": 900,
      "lastSeenAt": "2026-07-05T02:29:27.583936"
    },
    {
      "weiboNickname": "呆呆的可爱多_",
      "activeDevices": 2,
      "danmuSent": 872,
      "discussionSent": 0,
      "danmuFailed": 0,
      "discussionFailed": 0,
      "danmuSkipped": 0,
      "totalSent": 872,
      "lastSeenAt": "2026-07-05T02:26:38.244681"
    },
    {
      "weiboNickname": "次宝的炭宝",
      "activeDevices": 1,
      "danmuSent": 700,
      "discussionSent": 0,
      "danmuFailed": 0,
      "discussionFailed": 0,
      "danmuSkipped": 0,
      "totalSent": 700,
      "lastSeenAt": "2026-07-05T01:58:13.956653"
    },
    {
      "weiboNickname": "次次皆如初见",
      "activeDevices": 1,
      "danmuSent": 700,
      "discussionSent": 0,
      "danmuFailed": 0,
      "discussionFailed": 0,
      "danmuSkipped": 0,
      "totalSent": 700,
      "lastSeenAt": "2026-07-05T02:20:07.735588"
    },
    {
      "weiboNickname": "书荒人士",
      "activeDevices": 1,
      "danmuSent": 700,
      "discussionSent": 0,
      "danmuFailed": 0,
      "discussionFailed": 0,
      "danmuSkipped": 0,
      "totalSent": 700,
      "lastSeenAt": "2026-07-05T02:20:27.771092"
    },
    {
      "weiboNickname": "檀多多给我做饭",
      "activeDevices": 2,
      "danmuSent": 241,
      "discussionSent": 420,
      "danmuFailed": 0,
      "discussionFailed": 0,
      "danmuSkipped": 0,
      "totalSent": 661,
      "lastSeenAt": "2026-07-05T01:24:11.682961"
    },
    {
      "weiboNickname": "哆啦_T-HooHoo_",
      "activeDevices": 1,
      "danmuSent": 621,
      "discussionSent": 0,
      "danmuFailed": 0,
      "discussionFailed": 0,
      "danmuSkipped": 0,
      "totalSent": 621,
      "lastSeenAt": "2026-07-05T02:32:41.489628"
    },
    {
      "weiboNickname": "半唯T-HooHoo",
      "activeDevices": 1,
      "danmuSent": 600,
      "discussionSent": 0,
      "danmuFailed": 0,
      "discussionFailed": 0,
      "danmuSkipped": 0,
      "totalSent": 600,
      "lastSeenAt": "2026-07-05T02:30:29.026187"
    },
    {
      "weiboNickname": "檀檀颜颜",
      "activeDevices": 1,
      "danmuSent": 600,
      "discussionSent": 0,
      "danmuFailed": 0,
      "discussionFailed": 0,
      "danmuSkipped": 0,
      "totalSent": 600,
      "lastSeenAt": "2026-07-05T02:32:09.519651"
    },
    {
      "weiboNickname": "甜豆的T-hoohoo",
      "activeDevices": 1,
      "danmuSent": 600,
      "discussionSent": 0,
      "danmuFailed": 0,
      "discussionFailed": 0,
      "danmuSkipped": 0,
      "totalSent": 600,
      "lastSeenAt": "2026-07-05T02:36:11.761505"
    },
    {
      "weiboNickname": "檀猫猫的宝贝",
      "activeDevices": 1,
      "danmuSent": 561,
      "discussionSent": 0,
      "danmuFailed": 0,
      "discussionFailed": 0,
      "danmuSkipped": 0,
      "totalSent": 561,
      "lastSeenAt": "2026-07-05T02:21:12.880904"
    },
    {
      "weiboNickname": "躺尸的竹逐驻猪",
      "activeDevices": 1,
      "danmuSent": 0,
      "discussionSent": 500,
      "danmuFailed": 0,
      "discussionFailed": 0,
      "danmuSkipped": 0,
      "totalSent": 500,
      "lastSeenAt": "2026-07-05T02:17:11.156370"
    },
    {
      "weiboNickname": "仙女Pink爱种草",
      "activeDevices": 1,
      "danmuSent": 0,
      "discussionSent": 500,
      "danmuFailed": 0,
      "discussionFailed": 0,
      "danmuSkipped": 0,
      "totalSent": 500,
      "lastSeenAt": "2026-07-05T02:33:53.857044"
    },
    {
      "weiboNickname": "肥日小天使Hoo",
      "activeDevices": 1,
      "danmuSent": 101,
      "discussionSent": 360,
      "danmuFailed": 0,
      "discussionFailed": 0,
      "danmuSkipped": 0,
      "totalSent": 461,
      "lastSeenAt": "2026-07-05T02:03:00.030686"
    },
    {
      "weiboNickname": "檀琴雅致HooHoo",
      "activeDevices": 1,
      "danmuSent": 429,
      "discussionSent": 0,
      "danmuFailed": 0,
      "discussionFailed": 0,
      "danmuSkipped": 0,
      "totalSent": 429,
      "lastSeenAt": "2026-07-05T01:56:44.663422"
    },
    {
      "weiboNickname": "次次很健康",
      "activeDevices": 1,
      "danmuSent": 400,
      "discussionSent": 0,
      "danmuFailed": 0,
      "discussionFailed": 0,
      "danmuSkipped": 0,
      "totalSent": 400,
      "lastSeenAt": "2026-07-05T02:10:33.896201"
    },
    {
      "weiboNickname": "糖千晗",
      "activeDevices": 2,
      "danmuSent": 392,
      "discussionSent": 0,
      "danmuFailed": 0,
      "discussionFailed": 0,
      "danmuSkipped": 0,
      "totalSent": 392,
      "lastSeenAt": "2026-07-05T01:57:25.354369"
    },
    {
      "weiboNickname": "可以吃de青苹果",
      "activeDevices": 1,
      "danmuSent": 377,
      "discussionSent": 0,
      "danmuFailed": 0,
      "discussionFailed": 0,
      "danmuSkipped": 0,
      "totalSent": 377,
      "lastSeenAt": "2026-07-05T02:32:13.757859"
    },
    {
      "weiboNickname": "JCT-玖",
      "activeDevices": 1,
      "danmuSent": 364,
      "discussionSent": 0,
      "danmuFailed": 0,
      "discussionFailed": 0,
      "danmuSkipped": 0,
      "totalSent": 364,
      "lastSeenAt": "2026-07-05T02:25:51.867990"
    },
    {
      "weiboNickname": "猴酱_酷盖橘猫版",
      "activeDevices": 1,
      "danmuSent": 330,
      "discussionSent": 0,
      "danmuFailed": 0,
      "discussionFailed": 0,
      "danmuSkipped": 0,
      "totalSent": 330,
      "lastSeenAt": "2026-07-05T02:23:08.916577"
    },
    {
      "weiboNickname": "-TL檀小吉JC-",
      "activeDevices": 1,
      "danmuSent": 296,
      "discussionSent": 0,
      "danmuFailed": 0,
      "discussionFailed": 0,
      "danmuSkipped": 0,
      "totalSent": 296,
      "lastSeenAt": "2026-07-05T01:13:55.023847"
    },
    {
      "weiboNickname": "世界如此美好1988",
      "activeDevices": 1,
      "danmuSent": 256,
      "discussionSent": 0,
      "danmuFailed": 0,
      "discussionFailed": 0,
      "danmuSkipped": 0,
      "totalSent": 256,
      "lastSeenAt": "2026-07-05T01:06:10.752605"
    },
    {
      "weiboNickname": "檀亦次心",
      "activeDevices": 1,
      "danmuSent": 215,
      "discussionSent": 0,
      "danmuFailed": 0,
      "discussionFailed": 0,
      "danmuSkipped": 0,
      "totalSent": 215,
      "lastSeenAt": "2026-07-05T02:09:47.889437"
    },
    {
      "weiboNickname": "syou1005",
      "activeDevices": 1,
      "danmuSent": 204,
      "discussionSent": 0,
      "danmuFailed": 0,
      "discussionFailed": 0,
      "danmuSkipped": 0,
      "totalSent": 204,
      "lastSeenAt": "2026-07-05T01:19:45.673123"
    },
    {
      "weiboNickname": "Re晨曦-",
      "activeDevices": 1,
      "danmuSent": 200,
      "discussionSent": 0,
      "danmuFailed": 0,
      "discussionFailed": 0,
      "danmuSkipped": 0,
      "totalSent": 200,
      "lastSeenAt": "2026-07-05T01:46:38.973795"
    },
    {
      "weiboNickname": "Sarah猫小咪",
      "activeDevices": 1,
      "danmuSent": 200,
      "discussionSent": 0,
      "danmuFailed": 0,
      "discussionFailed": 0,
      "danmuSkipped": 0,
      "totalSent": 200,
      "lastSeenAt": "2026-07-05T02:35:57.522767"
    },
    {
      "weiboNickname": "吃一口冰球",
      "activeDevices": 1,
      "danmuSent": 0,
      "discussionSent": 184,
      "danmuFailed": 0,
      "discussionFailed": 0,
      "danmuSkipped": 0,
      "totalSent": 184,
      "lastSeenAt": "2026-07-05T00:47:39.599260"
    },
    {
      "weiboNickname": "钸町",
      "activeDevices": 1,
      "danmuSent": 0,
      "discussionSent": 143,
      "danmuFailed": 0,
      "discussionFailed": 0,
      "danmuSkipped": 0,
      "totalSent": 143,
      "lastSeenAt": "2026-07-05T02:33:51.594421"
    },
    {
      "weiboNickname": "赴檀之约-JCT",
      "activeDevices": 1,
      "danmuSent": 132,
      "discussionSent": 0,
      "danmuFailed": 0,
      "discussionFailed": 0,
      "danmuSkipped": 0,
      "totalSent": 132,
      "lastSeenAt": "2026-07-05T00:58:48.220999"
    },
    {
      "weiboNickname": "Coisini_HooHoo",
      "activeDevices": 1,
      "danmuSent": 101,
      "discussionSent": 0,
      "danmuFailed": 0,
      "discussionFailed": 0,
      "danmuSkipped": 0,
      "totalSent": 101,
      "lastSeenAt": "2026-07-05T02:36:17.489876"
    },
    {
      "weiboNickname": "DREAM S_Yy",
      "activeDevices": 1,
      "danmuSent": 0,
      "discussionSent": 100,
      "danmuFailed": 0,
      "discussionFailed": 0,
      "danmuSkipped": 0,
      "totalSent": 100,
      "lastSeenAt": "2026-07-05T00:27:30.988038"
    },
    {
      "weiboNickname": "忻忻年年大吉祥",
      "activeDevices": 1,
      "danmuSent": 28,
      "discussionSent": 0,
      "danmuFailed": 0,
      "discussionFailed": 0,
      "danmuSkipped": 0,
      "totalSent": 28,
      "lastSeenAt": "2026-07-05T00:14:43.663653"
    },
    {
      "weiboNickname": "Coisini-同舟渡版",
      "activeDevices": 1,
      "danmuSent": 21,
      "discussionSent": 0,
      "danmuFailed": 0,
      "discussionFailed": 0,
      "danmuSkipped": 0,
      "totalSent": 21,
      "lastSeenAt": "2026-07-05T00:03:27.791746"
    },
    {
      "weiboNickname": "6905777516",
      "activeDevices": 1,
      "danmuSent": 3,
      "discussionSent": 0,
      "danmuFailed": 0,
      "discussionFailed": 0,
      "danmuSkipped": 0,
      "totalSent": 3,
      "lastSeenAt": "2026-07-05T02:32:20.003226"
    },
    {
      "weiboNickname": "Mr_Tan小猫",
      "activeDevices": 1,
      "danmuSent": 0,
      "discussionSent": 0,
      "danmuFailed": 0,
      "discussionFailed": 0,
      "danmuSkipped": 0,
      "totalSent": 0,
      "lastSeenAt": "2026-07-05T02:05:37.118984"
    }
  ]
}
