{
  "schemaVersion": 1,
  "app": "biubiubiu_android",
  "date": "2026-07-05",
  "month": "2026-07",
  "updatedAt": "2026-07-04T16:36:45.695Z",
  "paths": {
    "counter": "archive/counters/2026/07/2026-07-05.json",
    "summary": "archive/summary/2026/2026-07.json"
  },
  "totals": {
    "date": "2026-07-05",
    "activeUsers": 36,
    "activeDevices": 56,
    "danmuSent": 7061,
    "discussionSent": 733,
    "danmuFailed": 0,
    "discussionFailed": 0,
    "danmuSkipped": 0,
    "lastSeenAt": "2026-07-05T00:36:02.234490",
    "updatedAt": "2026-07-04T16:36:44.163Z"
  },
  "users": [
    {
      "weiboNickname": "素颜多多JC-T",
      "activeDevices": 5,
      "danmuSent": 1503,
      "discussionSent": 0,
      "danmuFailed": 0,
      "discussionFailed": 0,
      "danmuSkipped": 0,
      "totalSent": 1503,
      "lastSeenAt": "2026-07-05T00:30:53.851417"
    },
    {
      "weiboNickname": "红丝丝儿",
      "activeDevices": 9,
      "danmuSent": 850,
      "discussionSent": 0,
      "danmuFailed": 0,
      "discussionFailed": 0,
      "danmuSkipped": 0,
      "totalSent": 850,
      "lastSeenAt": "2026-07-05T00:35:15.967032"
    },
    {
      "weiboNickname": "炭火炙笼包",
      "activeDevices": 1,
      "danmuSent": 652,
      "discussionSent": 0,
      "danmuFailed": 0,
      "discussionFailed": 0,
      "danmuSkipped": 0,
      "totalSent": 652,
      "lastSeenAt": "2026-07-05T00:33:13.247691"
    },
    {
      "weiboNickname": "邱邱T-HooHoo",
      "activeDevices": 1,
      "danmuSent": 604,
      "discussionSent": 0,
      "danmuFailed": 0,
      "discussionFailed": 0,
      "danmuSkipped": 0,
      "totalSent": 604,
      "lastSeenAt": "2026-07-05T00:32:55.968841"
    },
    {
      "weiboNickname": "檀了颗糖",
      "activeDevices": 2,
      "danmuSent": 400,
      "discussionSent": 0,
      "danmuFailed": 0,
      "discussionFailed": 0,
      "danmuSkipped": 0,
      "totalSent": 400,
      "lastSeenAt": "2026-07-05T00:33:28.336183"
    },
    {
      "weiboNickname": "晨光微暖JCT",
      "activeDevices": 2,
      "danmuSent": 300,
      "discussionSent": 0,
      "danmuFailed": 0,
      "discussionFailed": 0,
      "danmuSkipped": 0,
      "totalSent": 300,
      "lastSeenAt": "2026-07-05T00:33:28.887002"
    },
    {
      "weiboNickname": "桔梗花",
      "activeDevices": 3,
      "danmuSent": 291,
      "discussionSent": 0,
      "danmuFailed": 0,
      "discussionFailed": 0,
      "danmuSkipped": 0,
      "totalSent": 291,
      "lastSeenAt": "2026-07-05T00:24:45.389004"
    },
    {
      "weiboNickname": "檀多多给我做饭",
      "activeDevices": 2,
      "danmuSent": 88,
      "discussionSent": 173,
      "danmuFailed": 0,
      "discussionFailed": 0,
      "danmuSkipped": 0,
      "totalSent": 261,
      "lastSeenAt": "2026-07-05T00:34:33.637811"
    },
    {
      "weiboNickname": "次宝的炭宝",
      "activeDevices": 1,
      "danmuSent": 200,
      "discussionSent": 0,
      "danmuFailed": 0,
      "discussionFailed": 0,
      "danmuSkipped": 0,
      "totalSent": 200,
      "lastSeenAt": "2026-07-05T00:33:56.408963"
    },
    {
      "weiboNickname": "多多又man又healthy",
      "activeDevices": 1,
      "danmuSent": 200,
      "discussionSent": 0,
      "danmuFailed": 0,
      "discussionFailed": 0,
      "danmuSkipped": 0,
      "totalSent": 200,
      "lastSeenAt": "2026-07-05T00:33:11.282965"
    },
    {
      "weiboNickname": "小静姝吖",
      "activeDevices": 1,
      "danmuSent": 200,
      "discussionSent": 0,
      "danmuFailed": 0,
      "discussionFailed": 0,
      "danmuSkipped": 0,
      "totalSent": 200,
      "lastSeenAt": "2026-07-05T00:33:15.726363"
    },
    {
      "weiboNickname": "Glory-JCT",
      "activeDevices": 1,
      "danmuSent": 200,
      "discussionSent": 0,
      "danmuFailed": 0,
      "discussionFailed": 0,
      "danmuSkipped": 0,
      "totalSent": 200,
      "lastSeenAt": "2026-07-05T00:33:16.340975"
    },
    {
      "weiboNickname": "呆呆的可爱多_",
      "activeDevices": 2,
      "danmuSent": 172,
      "discussionSent": 0,
      "danmuFailed": 0,
      "discussionFailed": 0,
      "danmuSkipped": 0,
      "totalSent": 172,
      "lastSeenAt": "2026-07-05T00:28:36.401553"
    },
    {
      "weiboNickname": "平檀一生",
      "activeDevices": 2,
      "danmuSent": 0,
      "discussionSent": 160,
      "danmuFailed": 0,
      "discussionFailed": 0,
      "danmuSkipped": 0,
      "totalSent": 160,
      "lastSeenAt": "2026-07-05T00:24:51.802977"
    },
    {
      "weiboNickname": "哆啦_T-HooHoo_",
      "activeDevices": 1,
      "danmuSent": 121,
      "discussionSent": 0,
      "danmuFailed": 0,
      "discussionFailed": 0,
      "danmuSkipped": 0,
      "totalSent": 121,
      "lastSeenAt": "2026-07-05T00:25:11.199434"
    },
    {
      "weiboNickname": "世界如此美好1988",
      "activeDevices": 1,
      "danmuSent": 101,
      "discussionSent": 0,
      "danmuFailed": 0,
      "discussionFailed": 0,
      "danmuSkipped": 0,
      "totalSent": 101,
      "lastSeenAt": "2026-07-05T00:25:23.682493"
    },
    {
      "weiboNickname": "-TL檀小吉JC-",
      "activeDevices": 1,
      "danmuSent": 100,
      "discussionSent": 0,
      "danmuFailed": 0,
      "discussionFailed": 0,
      "danmuSkipped": 0,
      "totalSent": 100,
      "lastSeenAt": "2026-07-05T00:24:46.911668"
    },
    {
      "weiboNickname": "半唯T-HooHoo",
      "activeDevices": 1,
      "danmuSent": 100,
      "discussionSent": 0,
      "danmuFailed": 0,
      "discussionFailed": 0,
      "danmuSkipped": 0,
      "totalSent": 100,
      "lastSeenAt": "2026-07-05T00:25:10.140750"
    },
    {
      "weiboNickname": "吃一口冰球",
      "activeDevices": 1,
      "danmuSent": 0,
      "discussionSent": 100,
      "danmuFailed": 0,
      "discussionFailed": 0,
      "danmuSkipped": 0,
      "totalSent": 100,
      "lastSeenAt": "2026-07-05T00:29:23.915474"
    },
    {
      "weiboNickname": "次次皆如初见",
      "activeDevices": 1,
      "danmuSent": 100,
      "discussionSent": 0,
      "danmuFailed": 0,
      "discussionFailed": 0,
      "danmuSkipped": 0,
      "totalSent": 100,
      "lastSeenAt": "2026-07-05T00:19:59.322559"
    },
    {
      "weiboNickname": "赴檀之约-JCT",
      "activeDevices": 1,
      "danmuSent": 100,
      "discussionSent": 0,
      "danmuFailed": 0,
      "discussionFailed": 0,
      "danmuSkipped": 0,
      "totalSent": 100,
      "lastSeenAt": "2026-07-05T00:26:12.827143"
    },
    {
      "weiboNickname": "浓缩苦橙加冰茶",
      "activeDevices": 1,
      "danmuSent": 100,
      "discussionSent": 0,
      "danmuFailed": 0,
      "discussionFailed": 0,
      "danmuSkipped": 0,
      "totalSent": 100,
      "lastSeenAt": "2026-07-05T00:34:07.919073"
    },
    {
      "weiboNickname": "书荒人士",
      "activeDevices": 1,
      "danmuSent": 100,
      "discussionSent": 0,
      "danmuFailed": 0,
      "discussionFailed": 0,
      "danmuSkipped": 0,
      "totalSent": 100,
      "lastSeenAt": "2026-07-05T00:19:57.574193"
    },
    {
      "weiboNickname": "檀檀颜颜",
      "activeDevices": 1,
      "danmuSent": 100,
      "discussionSent": 0,
      "danmuFailed": 0,
      "discussionFailed": 0,
      "danmuSkipped": 0,
      "totalSent": 100,
      "lastSeenAt": "2026-07-05T00:24:57.033967"
    },
    {
      "weiboNickname": "躺尸的竹逐驻猪",
      "activeDevices": 1,
      "danmuSent": 0,
      "discussionSent": 100,
      "danmuFailed": 0,
      "discussionFailed": 0,
      "danmuSkipped": 0,
      "totalSent": 100,
      "lastSeenAt": "2026-07-05T00:24:31.877183"
    },
    {
      "weiboNickname": "甜豆的T-hoohoo",
      "activeDevices": 1,
      "danmuSent": 100,
      "discussionSent": 0,
      "danmuFailed": 0,
      "discussionFailed": 0,
      "danmuSkipped": 0,
      "totalSent": 100,
      "lastSeenAt": "2026-07-05T00:24:59.551577"
    },
    {
      "weiboNickname": "仙女Pink爱种草",
      "activeDevices": 1,
      "danmuSent": 0,
      "discussionSent": 100,
      "danmuFailed": 0,
      "discussionFailed": 0,
      "danmuSkipped": 0,
      "totalSent": 100,
      "lastSeenAt": "2026-07-05T00:26:37.199616"
    },
    {
      "weiboNickname": "DREAM S_Yy",
      "activeDevices": 1,
      "danmuSent": 0,
      "discussionSent": 100,
      "danmuFailed": 0,
      "discussionFailed": 0,
      "danmuSkipped": 0,
      "totalSent": 100,
      "lastSeenAt": "2026-07-05T00:27:30.988038"
    },
    {
      "weiboNickname": "糖千晗",
      "activeDevices": 2,
      "danmuSent": 92,
      "discussionSent": 0,
      "danmuFailed": 0,
      "discussionFailed": 0,
      "danmuSkipped": 0,
      "totalSent": 92,
      "lastSeenAt": "2026-07-05T00:16:59.755418"
    },
    {
      "weiboNickname": "檀琴雅致HooHoo",
      "activeDevices": 1,
      "danmuSent": 89,
      "discussionSent": 0,
      "danmuFailed": 0,
      "discussionFailed": 0,
      "danmuSkipped": 0,
      "totalSent": 89,
      "lastSeenAt": "2026-07-05T00:28:35.698205"
    },
    {
      "weiboNickname": "檀猫猫的宝贝",
      "activeDevices": 1,
      "danmuSent": 83,
      "discussionSent": 0,
      "danmuFailed": 0,
      "discussionFailed": 0,
      "danmuSkipped": 0,
      "totalSent": 83,
      "lastSeenAt": "2026-07-05T00:20:30.891388"
    },
    {
      "weiboNickname": "糖不好吃--YZZ",
      "activeDevices": 1,
      "danmuSent": 57,
      "discussionSent": 0,
      "danmuFailed": 0,
      "discussionFailed": 0,
      "danmuSkipped": 0,
      "totalSent": 57,
      "lastSeenAt": "2026-07-05T00:36:02.234490"
    },
    {
      "weiboNickname": "忻忻年年大吉祥",
      "activeDevices": 1,
      "danmuSent": 28,
      "discussionSent": 0,
      "danmuFailed": 0,
      "discussionFailed": 0,
      "danmuSkipped": 0,
      "totalSent": 28,
      "lastSeenAt": "2026-07-05T00:14:43.663653"
    },
    {
      "weiboNickname": "Coisini-同舟渡版",
      "activeDevices": 1,
      "danmuSent": 21,
      "discussionSent": 0,
      "danmuFailed": 0,
      "discussionFailed": 0,
      "danmuSkipped": 0,
      "totalSent": 21,
      "lastSeenAt": "2026-07-05T00:03:27.791746"
    },
    {
      "weiboNickname": "syou1005",
      "activeDevices": 1,
      "danmuSent": 9,
      "discussionSent": 0,
      "danmuFailed": 0,
      "discussionFailed": 0,
      "danmuSkipped": 0,
      "totalSent": 9,
      "lastSeenAt": "2026-07-05T00:04:10.220484"
    },
    {
      "weiboNickname": "可以吃de青苹果",
      "activeDevices": 1,
      "danmuSent": 0,
      "discussionSent": 0,
      "danmuFailed": 0,
      "discussionFailed": 0,
      "danmuSkipped": 0,
      "totalSent": 0,
      "lastSeenAt": "2026-07-05T00:16:40.014381"
    }
  ]
}
