{
  "schemaVersion": 1,
  "app": "biubiubiu_android",
  "date": "2026-07-20",
  "month": "2026-07",
  "updatedAt": "2026-07-19T18:10:22.319Z",
  "paths": {
    "counter": "archive/counters/2026/07/2026-07-20.json",
    "summary": "archive/summary/2026/2026-07.json"
  },
  "totals": {
    "date": "2026-07-20",
    "activeUsers": 10,
    "activeDevices": 12,
    "danmuSent": 3327,
    "discussionSent": 1300,
    "danmuFailed": 0,
    "discussionFailed": 0,
    "danmuSkipped": 0,
    "lastSeenAt": "2026-07-20T02:09:46.177059",
    "updatedAt": "2026-07-19T18:10:19.708Z"
  },
  "users": [
    {
      "weiboNickname": "平檀一生",
      "activeDevices": 2,
      "danmuSent": 1000,
      "discussionSent": 0,
      "danmuFailed": 0,
      "discussionFailed": 0,
      "danmuSkipped": 0,
      "totalSent": 1000,
      "lastSeenAt": "2026-07-20T01:57:16.404044"
    },
    {
      "weiboNickname": "晨光微暖JCT",
      "activeDevices": 2,
      "danmuSent": 700,
      "discussionSent": 0,
      "danmuFailed": 0,
      "discussionFailed": 0,
      "danmuSkipped": 0,
      "totalSent": 700,
      "lastSeenAt": "2026-07-20T02:01:05.445469"
    },
    {
      "weiboNickname": "檀檀颜颜",
      "activeDevices": 1,
      "danmuSent": 0,
      "discussionSent": 500,
      "danmuFailed": 0,
      "discussionFailed": 0,
      "danmuSkipped": 0,
      "totalSent": 500,
      "lastSeenAt": "2026-07-20T02:09:46.177059"
    },
    {
      "weiboNickname": "糖千晗",
      "activeDevices": 1,
      "danmuSent": 500,
      "discussionSent": 0,
      "danmuFailed": 0,
      "discussionFailed": 0,
      "danmuSkipped": 0,
      "totalSent": 500,
      "lastSeenAt": "2026-07-20T02:05:17.752750"
    },
    {
      "weiboNickname": "多多又man又healthy",
      "activeDevices": 1,
      "danmuSent": 452,
      "discussionSent": 0,
      "danmuFailed": 0,
      "discussionFailed": 0,
      "danmuSkipped": 0,
      "totalSent": 452,
      "lastSeenAt": "2026-07-20T01:16:02.299852"
    },
    {
      "weiboNickname": "多次一口巧克力",
      "activeDevices": 1,
      "danmuSent": 0,
      "discussionSent": 400,
      "danmuFailed": 0,
      "discussionFailed": 0,
      "danmuSkipped": 0,
      "totalSent": 400,
      "lastSeenAt": "2026-07-20T01:43:07.202321"
    },
    {
      "weiboNickname": "檀郎好联句",
      "activeDevices": 1,
      "danmuSent": 0,
      "discussionSent": 400,
      "danmuFailed": 0,
      "discussionFailed": 0,
      "danmuSkipped": 0,
      "totalSent": 400,
      "lastSeenAt": "2026-07-20T01:47:32.675899"
    },
    {
      "weiboNickname": "甜豆的T-hoohoo",
      "activeDevices": 1,
      "danmuSent": 300,
      "discussionSent": 0,
      "danmuFailed": 0,
      "discussionFailed": 0,
      "danmuSkipped": 0,
      "totalSent": 300,
      "lastSeenAt": "2026-07-20T01:15:04.706529"
    },
    {
      "weiboNickname": "呆呆的可爱多_",
      "activeDevices": 1,
      "danmuSent": 241,
      "discussionSent": 0,
      "danmuFailed": 0,
      "discussionFailed": 0,
      "danmuSkipped": 0,
      "totalSent": 241,
      "lastSeenAt": "2026-07-20T01:59:43.807613"
    },
    {
      "weiboNickname": "忻忻年年大吉祥",
      "activeDevices": 1,
      "danmuSent": 134,
      "discussionSent": 0,
      "danmuFailed": 0,
      "discussionFailed": 0,
      "danmuSkipped": 0,
      "totalSent": 134,
      "lastSeenAt": "2026-07-20T00:46:06.601589"
    }
  ]
}
